picframe/__init__.py
picframe/_version.py
picframe/controller.py
picframe/geo_reverse.py
picframe/get_image_meta.py
picframe/image_cache.py
picframe/interface_http.py
picframe/interface_mqtt.py
picframe/interface_peripherals.py
picframe/mat_image.py
picframe/model.py
picframe/start.py
picframe/video_metadata.py
picframe/video_player.py
picframe/video_streamer.py
picframe/viewer_display.py
picframe/config/configuration_example.yaml
picframe/data/no_pictures.jpg
picframe/data/fonts/LICENSE.txt
picframe/data/fonts/NotoSans-Bold.ttf
picframe/data/fonts/NotoSans-BoldItalic.ttf
picframe/data/fonts/NotoSans-Italic.ttf
picframe/data/fonts/NotoSans-Regular.ttf
picframe/data/mat/9_patch_bevel.png
picframe/data/mat/9_patch_drop_shadow.png
picframe/data/mat/9_patch_highlight.png
picframe/data/mat/9_patch_inner_shadow.png
picframe/data/mat/mat_texture.jpg
picframe/data/shaders/blend_new.fs
picframe/data/shaders/blend_new.vs
picframe/html/index.html
picframe/html/pf_functions.js
picframe-2025.6.18.dist-info/licenses/LICENSE
picframe-2025.6.18.dist-info/METADATA
picframe-2025.6.18.dist-info/WHEEL
picframe-2025.6.18.dist-info/entry_points.txt
picframe-2025.6.18.dist-info/top_level.txt
picframe-2025.6.18.dist-info/RECORD
