Metadata-Version: 2.4
Name: picframe
Version: 2025.6.18
Summary: Picture frame viewer powered by raspberry with homeassistant integration
Author: Paddy Gaunt, Jeff Godfrey
Author-email: Helge Erbe <helge@erbehome.de>
Maintainer-email: Helge Erbe <helge@erbehome.de>
License: MIT
Project-URL: Homepage, https://github.com/helgeerbe/picframe
Keywords: picframe,viewer,raspberry,raspi,homeassistant,hass
Classifier: Development Status :: 4 - Beta
Classifier: License :: OSI Approved :: MIT License
Classifier: Programming Language :: Python
Classifier: Programming Language :: Python :: 3
Classifier: Programming Language :: Python :: 3.11
Classifier: Programming Language :: Python :: 3.12
Classifier: Programming Language :: Python :: 3.13
Classifier: Topic :: Multimedia :: Graphics :: Viewers
Requires-Python: >=3.7
License-File: LICENSE
Requires-Dist: Pillow>=10.2.0
Requires-Dist: defusedxml
Requires-Dist: pi3d>=2.54
Requires-Dist: PyYAML
Requires-Dist: paho-mqtt>=2.1.0
Requires-Dist: IPTCInfo3
Requires-Dist: numpy
Requires-Dist: ninepatch>=0.2.0
Requires-Dist: pi_heif>=0.8.0
Requires-Dist: python-vlc
Requires-Dist: rubicon-objc; sys_platform == "darwin"
Dynamic: license-file
